db_facade/__init__.py
db_facade/db.py
db_facade-0.0.7a0.dist-info/LICENSE
db_facade-0.0.7a0.dist-info/METADATA
db_facade-0.0.7a0.dist-info/WHEEL
db_facade-0.0.7a0.dist-info/top_level.txt
db_facade-0.0.7a0.dist-info/RECORD
